dependable/__init__.py
dependable/concurrency.py
dependable/core.py
dependable/decorator.py
dependable/utils.py
dependable-0.1.0.dist-info/LICENSE
dependable-0.1.0.dist-info/WHEEL
dependable-0.1.0.dist-info/METADATA
dependable-0.1.0.dist-info/RECORD
